speckle/Cache.py
speckle/SpeckleClient.py
speckle/__init__.py
speckle/base/__init__.py
speckle/base/client.py
speckle/base/resource.py
speckle/resources/__init__.py
speckle/resources/accounts.py
speckle/resources/api_clients.py
speckle/resources/comments.py
speckle/resources/objects.py
speckle/resources/projects.py
speckle/resources/streams.py
speckle/schemas/Arc.py
speckle/schemas/Brep.py
speckle/schemas/Curve.py
speckle/schemas/Interval.py
speckle/schemas/Line.py
speckle/schemas/Mesh.py
speckle/schemas/Null.py
speckle/schemas/Number.py
speckle/schemas/Plane.py
speckle/schemas/Point.py
speckle/schemas/Polycurve.py
speckle/schemas/Polyline.py
speckle/schemas/String.py
speckle/schemas/Vector.py
speckle/schemas/__init__.py
speckle-2.3.0.dist-info/LICENSE
speckle-2.3.0.dist-info/METADATA
speckle-2.3.0.dist-info/WHEEL
speckle-2.3.0.dist-info/top_level.txt
speckle-2.3.0.dist-info/RECORD
