Metadata-Version: 2.1
Name: speckle
Version: 2.3.0
Summary: A Python client for Speckle servers.
Home-page: https://github.com/specklworks/pyspeckle
Author: Speckle Works
Author-email: devops@speckle.works
License: UNKNOWN
Platform: UNKNOWN
Classifier: Programming Language :: Python :: 3.6
Classifier: Operating System :: OS Independent
Requires-Dist: astroid (==2.2.5)
Requires-Dist: atomicwrites (==1.3.0)
Requires-Dist: attrs (==19.1.0)
Requires-Dist: certifi (==2019.3.9)
Requires-Dist: chardet (==3.0.4)
Requires-Dist: dataclasses (==0.6)
Requires-Dist: idna (==2.8)
Requires-Dist: isort (==4.3.20)
Requires-Dist: lazy-object-proxy (==1.4.1)
Requires-Dist: mccabe (==0.6.1)
Requires-Dist: more-itertools (==7.0.0)
Requires-Dist: pluggy (==0.11.0)
Requires-Dist: py (==1.8.0)
Requires-Dist: pydantic (==1.4)
Requires-Dist: requests (==2.22.0)
Requires-Dist: six (==1.12.0)
Requires-Dist: typed-ast (==1.4.1)
Requires-Dist: urllib3 (==1.25.3)
Requires-Dist: wcwidth (==0.1.7)
Requires-Dist: wrapt (==1.11.1)
Requires-Dist: websockets (==7.0)
Requires-Dist: websocket-client (==0.56.0)
